MANIFEST.in
README.rst
setup.py
pyramid_maze/__init__.py
pyramid_maze/helpers.py
pyramid_maze/maze.py
pyramid_maze.egg-info/PKG-INFO
pyramid_maze.egg-info/SOURCES.txt
pyramid_maze.egg-info/dependency_links.txt
pyramid_maze.egg-info/requires.txt
pyramid_maze.egg-info/top_level.txt