Metadata-Version: 1.0
Name: pyramid-maze
Version: 1.0.0
Summary: A url route generator for Pyramid's traversal, based on graph theory
Home-page: https://github.com/mahmoudimus/pyramid_maze
Author: mahmoudimus
Author-email: mabdelkader@gmail.com
License: UNKNOWN
Platform: any
Classifier: Development Status :: 4 - Beta
Classifier: Intended Audience :: Developers
Classifier: Natural Language :: English
Classifier: License :: OSI Approved :: ISC License (ISCL)
Classifier: Programming Language :: Python
Classifier: Programming Language :: Python :: 2.7
